[
  {"lesson": 1, "title": "古诗三首", "type": "课文", "unit": 1, "characters": [
    {"char": "融", "words": ["融化", "融合", "融洽"]},
    {"char": "燕", "words": ["燕子", "燕尾", "家燕"]},
    {"char": "鸳", "words": ["鸳鸯"]},
    {"char": "鸯", "words": ["鸳鸯"]},
    {"char": "惠", "words": ["恩惠", "实惠", "惠崇"]},
    {"char": "崇", "words": ["崇高", "崇敬", "崇拜"]},
    {"char": "芦", "words": ["芦苇", "芦花", "芦笋"]},
    {"char": "芽", "words": ["发芽", "豆芽", "嫩芽"]},
    {"char": "梅", "words": ["梅花", "腊梅", "杨梅"]},
    {"char": "溪", "words": ["小溪", "溪水", "溪流"]},
    {"char": "泛", "words": ["泛舟", "广泛", "泛滥"]},
    {"char": "减", "words": ["减少", "减法", "减轻"]}
  ]},
  {"lesson": 2, "title": "燕子", "type": "课文", "unit": 1, "characters": [
    {"char": "凑", "words": ["凑成", "凑近", "凑合"]},
    {"char": "拂", "words": ["吹拂", "拂过", "春风拂面"]},
    {"char": "聚", "words": ["聚集", "聚会", "团聚"]},
    {"char": "形", "words": ["形状", "图形", "形成"]},
    {"char": "掠", "words": ["掠过"]},
    {"char": "偶", "words": ["偶尔", "偶然"]},
    {"char": "尔", "words": ["偶尔"]},
    {"char": "沾", "words": ["沾水", "沾光"]},
    {"char": "倦", "words": ["疲倦", "倦意", "厌倦"]},
    {"char": "纤", "words": ["纤细", "纤维"]},
    {"char": "痕", "words": ["痕迹", "泪痕", "伤痕"]}
  ]},
  {"lesson": 3, "title": "荷花", "type": "课文", "unit": 1, "characters": [
    {"char": "瓣", "words": ["花瓣", "蒜瓣"]},
    {"char": "蓬", "words": ["莲蓬", "蓬松", "蓬勃"]},
    {"char": "胀", "words": ["膨胀", "肿胀", "饱胀"]},
    {"char": "仿", "words": ["仿佛", "模仿", "仿照"]},
    {"char": "佛", "words": ["仿佛", "佛像"]},
    {"char": "裳", "words": ["衣裳"]},
    {"char": "翩", "words": ["翩翩起舞"]},
    {"char": "蜻", "words": ["蜻蜓"]},
    {"char": "蜓", "words": ["蜻蜓"]}
  ]},
  {"lesson": 4, "title": "昆虫备忘录", "type": "课文", "unit": 1, "characters": [
    {"char": "录", "words": ["记录", "录音", "录像"]},
    {"char": "款", "words": ["款式", "条款", "拨款"]},
    {"char": "绸", "words": ["绸子", "丝绸"]},
    {"char": "瞎", "words": ["瞎说", "瞎闹", "眼瞎"]},
    {"char": "益", "words": ["益虫", "有益", "利益"]},
    {"char": "约", "words": ["大约", "约定", "节约"]}
  ]},
  {"lesson": 5, "title": "守株待兔", "type": "课文", "unit": 2, "characters": [
    {"char": "守", "words": ["守护", "看守", "遵守"]},
    {"char": "株", "words": ["守株待兔", "植株"]},
    {"char": "待", "words": ["等待", "对待", "招待"]},
    {"char": "宋", "words": ["宋朝", "宋代"]},
    {"char": "耕", "words": ["耕田", "耕地", "耕种"]},
    {"char": "触", "words": ["触角", "接触", "感触"]},
    {"char": "颈", "words": ["颈部", "脖颈"]},
    {"char": "释", "words": ["解释", "释放", "释义"]}
  ]},
  {"lesson": 6, "title": "陶罐和铁罐", "type": "课文", "unit": 2, "characters": [
    {"char": "骄", "words": ["骄傲", "天骄", "骄横"]},
    {"char": "傲", "words": ["骄傲", "傲慢", "高傲"]},
    {"char": "谦", "words": ["谦虚", "谦让", "谦逊"]},
    {"char": "虚", "words": ["谦虚", "虚假", "虚心"]},
    {"char": "嘴", "words": ["嘴巴", "嘴唇"]},
    {"char": "懦", "words": ["懦弱", "懦夫"]},
    {"char": "弱", "words": ["弱小", "虚弱", "懦弱"]},
    {"char": "尘", "words": ["灰尘", "尘土", "风尘"]},
    {"char": "捧", "words": ["捧起", "捧着", "追捧"]},
    {"char": "代", "words": ["时代", "古代", "代替"]},
    {"char": "价", "words": ["价值", "价格", "价钱"]}
  ]},
  {"lesson": 9, "title": "古诗三首", "type": "课文", "unit": 3, "characters": [
    {"char": "屠", "words": ["屠苏", "屠宰"]},
    {"char": "苏", "words": ["苏醒", "复苏", "苏州"]},
    {"char": "符", "words": ["符合", "春联", "桃符"]},
    {"char": "欲", "words": ["欲望", "食欲"]},
    {"char": "魂", "words": ["灵魂", "魂魄", "销魂"]},
    {"char": "借", "words": ["借书", "借口", "借用"]},
    {"char": "酒", "words": ["白酒", "酒杯", "饮酒"]},
    {"char": "牧", "words": ["牧童", "牧羊", "牧场"]},
    {"char": "兄", "words": ["兄弟", "兄长", "师兄"]},
    {"char": "独", "words": ["独自", "孤独", "独立"]}
  ]},
  {"lesson": 10, "title": "纸的发明", "type": "课文", "unit": 3, "characters": [
    {"char": "术", "words": ["技术", "美术", "艺术"]},
    {"char": "伟", "words": ["伟大", "宏伟", "伟人"]},
    {"char": "录", "words": ["记录", "录像", "目录"]},
    {"char": "册", "words": ["书册", "手册", "上册"]},
    {"char": "保", "words": ["保存", "保护", "保持"]},
    {"char": "存", "words": ["保存", "存在", "存放"]},
    {"char": "验", "words": ["经验", "实验", "考验"]},
    {"char": "阿", "words": ["阿姨", "阿爸"]},
    {"char": "欧", "words": ["欧洲", "欧洲人"]},
    {"char": "洲", "words": ["亚洲", "欧洲", "非洲"]},
    {"char": "社", "words": ["社会", "社区", "社团"]}
  ]},
  {"lesson": 13, "title": "花钟", "type": "课文", "unit": 4, "characters": [
    {"char": "斗", "words": ["斗争", "战斗", "奋斗"]},
    {"char": "芬", "words": ["芬芳"]},
    {"char": "芳", "words": ["芬芳", "芳香"]},
    {"char": "内", "words": ["内部", "室内", "内容"]},
    {"char": "醒", "words": ["苏醒", "清醒", "叫醒"]},
    {"char": "寿", "words": ["长寿", "寿命", "祝寿"]},
    {"char": "苏", "words": ["苏醒", "复苏"]},
    {"char": "强", "words": ["强大", "强壮", "坚强"]},
    {"char": "示", "words": ["表示", "指示", "展示"]},
    {"char": "昆", "words": ["昆虫", "昆明"]}
  ]},
  {"lesson": 14, "title": "蜜蜂", "type": "课文", "unit": 4, "characters": [
    {"char": "蜜", "words": ["蜜蜂", "甜蜜", "蜂蜜"]},
    {"char": "蜂", "words": ["蜜蜂", "蜂巢", "蜂王"]},
    {"char": "辨", "words": ["辨别", "分辨", "辨认"]},
    {"char": "阻", "words": ["阻力", "阻止", "阻碍"]},
    {"char": "跨", "words": ["跨越", "跨过", "横跨"]},
    {"char": "括", "words": ["包括", "括号"]},
    {"char": "检", "words": ["检查", "检测", "体检"]},
    {"char": "查", "words": ["检查", "调查", "查看"]},
    {"char": "确", "words": ["确定", "正确", "确实"]},
    {"char": "误", "words": ["错误", "耽误", "误会"]},
    {"char": "途", "words": ["途中", "路途", "前途"]},
    {"char": "陌", "words": ["陌生"]}
  ]},
  {"lesson": 17, "title": "我变成了一棵树", "type": "课文", "unit": 5, "characters": [
    {"char": "希", "words": ["希望", "希求"]},
    {"char": "痒", "words": ["痒痒", "发痒", "手痒"]},
    {"char": "鳄", "words": ["鳄鱼"]},
    {"char": "丁", "words": ["丁冬", "园丁", "家丁"]},
    {"char": "零", "words": ["零食", "零件", "零分"]},
    {"char": "肠", "words": ["香肠", "肠子", "肠胃"]},
    {"char": "继", "words": ["继续", "继承", "后继"]},
    {"char": "续", "words": ["继续", "持续", "连续"]},
    {"char": "秘", "words": ["秘密", "秘书", "神秘"]},
    {"char": "密", "words": ["秘密", "密码", "紧密"]}
  ]}
]
